{
    "USB Connection": 10001,
    "New Segment": 99999,
    "Stimulus/1_0": 1,
    "Stimulus/1_50": 2,
    "Stimulus/1_100": 3,
    "Stimulus/1_150": 4,
    "Stimulus/1_0_R": 5,
    "Stimulus/1_50_R": 6,
    "Stimulus/1_100_R": 7,
    "Stimulus/1_150_R": 8,
    "Stimulus/2_0": 9,
    "Stimulus/2_50": 10,
    "Stimulus/2_100": 11,
    "Stimulus/2_150": 12,
    "Stimulus/2_0_R": 13,
    "Stimulus/2_50_R": 14,
    "Stimulus/2_100_R": 15,
    "Stimulus/2_150_R": 16,
    "Stimulus/3_0": 17,
    "Stimulus/3_50": 18,
    "Stimulus/3_100": 19,
    "Stimulus/3_150": 20,
    "Stimulus/3_0_R": 21,
    "Stimulus/3_50_R": 22,
    "Stimulus/3_100_R": 23,
    "Stimulus/3_150_R": 24,
    "Stimulus/4_0": 25,
    "Stimulus/4_50": 26,
    "Stimulus/4_100": 27,
    "Stimulus/4_150": 28,
    "Stimulus/4_0_R": 29,
    "Stimulus/4_50_R": 30,
    "Stimulus/4_100_R": 31,
    "Stimulus/4_150_R": 32,
    "Stimulus/5_0": 33,
    "Stimulus/5_50": 34,
    "Stimulus/5_100": 35,
    "Stimulus/5_150": 36,
    "Stimulus/5_0_R": 37,
    "Stimulus/5_50_R": 38,
    "Stimulus/5_100_R": 39,
    "Stimulus/5_150_R": 40,
    "Stimulus/6_0": 41,
    "Stimulus/6_50": 42,
    "Stimulus/6_100": 43,
    "Stimulus/6_150": 44,
    "Stimulus/6_0_R": 45,
    "Stimulus/6_50_R": 46,
    "Stimulus/6_100_R": 47,
    "Stimulus/6_150_R": 48,
    "Stimulus/7_0": 49,
    "Stimulus/7_50": 50,
    "Stimulus/7_100": 51,
    "Stimulus/7_150": 52,
    "Stimulus/7_0_R": 53,
    "Stimulus/7_50_R": 54,
    "Stimulus/7_100_R": 55,
    "Stimulus/7_150_R": 56,
    "Stimulus/8_0": 57,
    "Stimulus/8_50": 58,
    "Stimulus/8_100": 59,
    "Stimulus/8_150": 60,
    "Stimulus/8_0_R": 61,
    "Stimulus/8_50_R": 62,
    "Stimulus/8_100_R": 63,
    "Stimulus/8_150_R": 64,
    "Stimulus/9_0": 65,
    "Stimulus/9_50": 66,
    "Stimulus/9_100": 67,
    "Stimulus/9_150": 68,
    "Stimulus/9_0_R": 69,
    "Stimulus/9_50_R": 70,
    "Stimulus/9_100_R": 71,
    "Stimulus/9_150_R": 72,
    "Stimulus/10_0": 73,
    "Stimulus/10_50": 74,
    "Stimulus/10_100": 75,
    "Stimulus/10_150": 76,
    "Stimulus/10_0_R": 77,
    "Stimulus/10_50_R": 78,
    "Stimulus/10_100_R": 79,
    "Stimulus/10_150_R": 80,
    "Stimulus/39_0": 81,
    "Stimulus/39_50": 82,
    "Stimulus/39_100": 83,
    "Stimulus/39_150": 84,
    "Stimulus/39_0_R": 85,
    "Stimulus/39_50_R": 86,
    "Stimulus/39_100_R": 87,
    "Stimulus/39_150_R": 88,
    "Stimulus/40_0": 89,
    "Stimulus/40_50": 90,
    "Stimulus/40_100": 91,
    "Stimulus/40_150": 92,
    "Stimulus/40_0_R": 93,
    "Stimulus/40_50_R": 94,
    "Stimulus/40_100_R": 95,
    "Stimulus/40_150_R": 96,
    "Stimulus/41_0": 97,
    "Stimulus/41_50": 98,
    "Stimulus/41_100": 99,
    "Stimulus/41_150": 100,
    "Stimulus/41_0_R": 101,
    "Stimulus/41_50_R": 102,
    "Stimulus/41_100_R": 103,
    "Stimulus/41_150_R": 104,
    "Stimulus/42_0": 105,
    "Stimulus/42_50": 106,
    "Stimulus/42_100": 107,
    "Stimulus/42_150": 108,
    "Stimulus/42_0_R": 109,
    "Stimulus/42_50_R": 110,
    "Stimulus/42_100_R": 111,
    "Stimulus/42_150_R": 112,
    "Stimulus/43_0": 113,
    "Stimulus/43_50": 114,
    "Stimulus/43_100": 115,
    "Stimulus/43_150": 116,
    "Stimulus/43_0_R": 117,
    "Stimulus/43_50_R": 118,
    "Stimulus/43_100_R": 119,
    "Stimulus/43_150_R": 120,
    "Stimulus/44_0": 121,
    "Stimulus/44_50": 122,
    "Stimulus/44_100": 123,
    "Stimulus/44_150": 124,
    "Stimulus/44_0_R": 125,
    "Stimulus/44_50_R": 126,
    "Stimulus/44_100_R": 127,
    "Stimulus/44_150_R": 128,
    "Stimulus/45_0": 129,
    "Stimulus/45_50": 130,
    "Stimulus/45_100": 131,
    "Stimulus/45_150": 132,
    "Stimulus/45_0_R": 133,
    "Stimulus/45_50_R": 134,
    "Stimulus/45_100_R": 135,
    "Stimulus/45_150_R": 136,
    "Stimulus/46_0": 137,
    "Stimulus/46_50": 138,
    "Stimulus/46_100": 139,
    "Stimulus/46_150": 140,
    "Stimulus/46_0_R": 141,
    "Stimulus/46_50_R": 142,
    "Stimulus/46_100_R": 143,
    "Stimulus/46_150_R": 144,
    "Stimulus/47_0": 145,
    "Stimulus/47_50": 146,
    "Stimulus/47_100": 147,
    "Stimulus/47_150": 148,
    "Stimulus/47_0_R": 149,
    "Stimulus/47_50_R": 150,
    "Stimulus/47_100_R": 151,
    "Stimulus/47_150_R": 152,
    "Stimulus/48_0": 153,
    "Stimulus/48_50": 154,
    "Stimulus/48_100": 155,
    "Stimulus/48_150": 156,
    "Stimulus/48_0_R": 157,
    "Stimulus/48_50_R": 158,
    "Stimulus/48_100_R": 159,
    "Stimulus/48_150_R": 160,
    "Response/Same": 251,
    "Response/Different": 252
}